trilobot/__init__.py
trilobot/controller_mappings.py
trilobot/simple_controller.py
trilobot-0.0.2.dist-info/LICENSE.txt
trilobot-0.0.2.dist-info/METADATA
trilobot-0.0.2.dist-info/WHEEL
trilobot-0.0.2.dist-info/top_level.txt
trilobot-0.0.2.dist-info/RECORD
