Metadata-Version: 2.1
Name: trilobot
Version: 0.0.2
Summary: Trilobot, a mid-level robot learning platform aimed at the Rasberry Pi SBC range
Home-page: https://www.pimoroni.com
Author: Christopher Parrott
Author-email: chris@pimoroni.com
License: MIT
Project-URL: GitHub, https://www.github.com/pimoroni/trilobot-python
Keywords: Raspberry Pi
Platform: UNKNOWN
Classifier: Development Status :: 4 - Beta
Classifier: Operating System :: POSIX :: Linux
Classifier: License :: OSI Approved :: MIT License
Classifier: Intended Audience :: Developers
Classifier: Programming Language :: Python :: 2.7
Classifier: Programming Language :: Python :: 3
Classifier: Topic :: Software Development
Classifier: Topic :: Software Development :: Libraries
Classifier: Topic :: System :: Hardware
Requires-Python: >=2.7
License-File: LICENSE.txt
Requires-Dist: evdev
Requires-Dist: sn3218 (>=2.0.0)
